wiptools/__init__.py
wiptools/cookiecutters/CLI/cookiecutter.json
wiptools/cookiecutters/CLI/{{cookiecutter.cli_name}}/__main__.py
wiptools/cookiecutters/CLI-tests/cookiecutter.json
wiptools/cookiecutters/CLI-tests/{{cookiecutter.cli_name}}/test_{{cookiecutter.cli_name}}.py
wiptools/cookiecutters/CLIsub/cookiecutter.json
wiptools/cookiecutters/CLIsub/{{cookiecutter.cli_name}}/__main__.py
wiptools/cookiecutters/CLIsub-tests/cookiecutter.json
wiptools/cookiecutters/CLIsub-tests/{{cookiecutter.cli_name}}/test_{{cookiecutter.cli_name}}.py
wiptools/cookiecutters/module-cpp/cookiecutter.json
wiptools/cookiecutters/module-cpp/{{cookiecutter.module_name}}/CMakeLists.txt
wiptools/cookiecutters/module-cpp/{{cookiecutter.module_name}}/{{cookiecutter.module_name}}.cpp
wiptools/cookiecutters/module-cpp/{{cookiecutter.module_name}}/{{cookiecutter.module_name}}.md
wiptools/cookiecutters/module-cpp-tests/cookiecutter.json
wiptools/cookiecutters/module-cpp-tests/{{cookiecutter.module_name}}/test_{{cookiecutter.module_name}}.py
wiptools/cookiecutters/module-f90/cookiecutter.json
wiptools/cookiecutters/module-f90/{{cookiecutter.module_name}}/CMakeLists.txt
wiptools/cookiecutters/module-f90/{{cookiecutter.module_name}}/{{cookiecutter.module_name}}.f90
wiptools/cookiecutters/module-f90/{{cookiecutter.module_name}}/{{cookiecutter.module_name}}.md
wiptools/cookiecutters/module-f90-tests/cookiecutter.json
wiptools/cookiecutters/module-f90-tests/{{cookiecutter.module_name}}/test_{{cookiecutter.module_name}}.py
wiptools/cookiecutters/module-py/cookiecutter.json
wiptools/cookiecutters/module-py/{{cookiecutter.module_name}}/__init__.py
wiptools/cookiecutters/module-py-tests/cookiecutter.json
wiptools/cookiecutters/module-py-tests/{{cookiecutter.module_name}}/test_{{cookiecutter.module_name}}.py
wiptools/cookiecutters/project/cookiecutter.json
wiptools/cookiecutters/project/{{cookiecutter.project_name}}/.bumpversion.cfg
wiptools/cookiecutters/project/{{cookiecutter.project_name}}/.gitignore
wiptools-1.3.2.dist-info/METADATA
wiptools-1.3.2.dist-info/WHEEL
wiptools-1.3.2.dist-info/entry_points.txt
wiptools-1.3.2.dist-info/RECORD
