Metadata-Version: 2.1
Name: wiptools
Version: 1.3.2
Summary: Python project skeleton and management
Home-page: https://etijskens.github.io/wiptools
License: MIT
Author: Bert Tijskens
Author-email: engelbert.tijskens@uantwerpen.be
Requires-Python: >=3.9,<4.0
Classifier: License :: OSI Approved :: MIT License
Classifier: Programming Language :: Python :: 3
Classifier: Programming Language :: Python :: 3.9
Classifier: Programming Language :: Python :: 3.10
Classifier: Programming Language :: Python :: 3.11
Requires-Dist: click (>=8.1.3,<9.0.0)
Requires-Dist: cookiecutter (>=2.1.1,<3.0.0)
Requires-Dist: packaging (>=23.1,<24.0)
Requires-Dist: tomlkit (>=0.11.8,<0.12.0)
Project-URL: Repository, https://github.com/etijskens/wiptools
